Metadata-Version: 1.1
Name: zake
Version: 0.0.14
Summary: A python package that works to provide a nice set of testing utilities for the kazoo library.
Home-page: https://github.com/yahoo/Zake
Author: Joshua Harlow
Author-email: harlowja@yahoo-inc.com
License: ASL 2.0
Keywords: kazoo testing zookeeper
Platform: UNKNOWN
Classifier: Development Status :: 4 - Beta
Classifier: Topic :: Utilities
Classifier: License :: OSI Approved :: Apache Software License
Classifier: Operating System :: POSIX :: Linux
Classifier: Programming Language :: Python
